billsplitter.py
billsplitter-1.0.1.dist-info/LICENSE
billsplitter-1.0.1.dist-info/METADATA
billsplitter-1.0.1.dist-info/WHEEL
billsplitter-1.0.1.dist-info/entry_points.txt
billsplitter-1.0.1.dist-info/top_level.txt
billsplitter-1.0.1.dist-info/RECORD
